{
  "taggedSentenceList": [
    {
      "intent.teainfo": [
        "[TEA:TEA]보리차[/TEA:TEA] 말해줘",
        "[TEA:TEA]레몬차[/TEA:TEA] 설명해줘",
        "[TEA:TEA]케모마일차[/TEA:TEA] 알려줘",
        "[TEA:TEA]레몬차[/TEA:TEA]의 좋은 점",
        "[TEA:TEA]케모마일[/TEA:TEA]의 정보를 알려줘",
        "[TEA:TEA]오미자차[/TEA:TEA]",
        "[TEA:TEA]도자리차[/TEA:TEA]는 뭐야",
        "[TEA:TEA]생강차[/TEA:TEA]는 어디가 좋아",
        "[TEA:TEA]녹차[/TEA:TEA]의 효능",
        "[TEA:TEA]우롱차[/TEA:TEA]에 대해서 알려줘"
      ],
      "intent.help": [
        "설명을 알려줘",
        "메뉴얼을 알려줘",
        "메뉴얼",
        "매뉴얼",
        "어떻게 사용하는거야",
        "사용법을 알려줘",
        "설명서",
        "헬프",
        "도움말"
      ]
    }
  ],
  "userDictList": [
    {
      "TEA": {
        "오미자차": [
          "오미자"
        ],
        "홍차": [],
        "도라지차": [
          "도라지"
        ],
        "모과차": [
          "모과"
        ],
        "우롱차": [],
        "자스민차": [
          "자스민"
        ],
        "보리차": [
          "보리"
        ],
        "우엉차": [
          "우엉"
        ],
        "대추차": [
          "대추"
        ],
        "레몬차": [
          "레몬"
        ],
        "메밀차": [
          "메밀"
        ],
        "천일홍차": [
          "천일홍"
        ],
        "페퍼민트차": [
          "페퍼민트"
        ],
        "감잎차": [
          "감잎"
        ],
        "생강차": [
          "생강"
        ],
        "녹차": [],
        "유자차": [
          "유자"
        ],
        "캐모마일차": [
          "케모마일",
          "케모마일차",
          "캐모마일"
        ],
        "루이보스차": [
          "루이보스"
        ],
        "라벤더차": [
          "라벤다",
          "라벤다차",
          "라벤더"
        ]
      }
    }
  ]
}